yescaptcha_py/__init__.py
yescaptcha_py/cf_cookie.py
yescaptcha_py/cf_turnstile.py
yescaptcha_py/recaptcha_v2.py
yescaptcha_py/version.py
yescaptcha_py-0.0.3.dist-info/licenses/LICENSE
yescaptcha_py-0.0.3.dist-info/METADATA
yescaptcha_py-0.0.3.dist-info/WHEEL
yescaptcha_py-0.0.3.dist-info/top_level.txt
yescaptcha_py-0.0.3.dist-info/RECORD
