Metadata-Version: 2.4
Name: yescaptcha-py
Version: 0.0.3
Summary: yescaptcha python package
Home-page: https://github.com/zefzhou/yescaptcha-py
Author: zefzhou44
Author-email: zefzhou44@gmail.com
Classifier: Programming Language :: Python :: 3
Classifier: License :: OSI Approved :: MIT License
Classifier: Operating System :: OS Independent
Requires-Python: >=3.8.0
License-File: LICENSE
Requires-Dist: loguru>=0.7.2
Requires-Dist: Requests>=2.32.3
Requires-Dist: aiohttp>=3.12.13
Dynamic: author
Dynamic: author-email
Dynamic: classifier
Dynamic: description
Dynamic: description-content-type
Dynamic: home-page
Dynamic: license-file
Dynamic: requires-dist
Dynamic: requires-python
Dynamic: summary
